yta_multimedia/__init__.py
yta_multimedia/alphascreen/__init__.py
yta_multimedia/alphascreen/alphascreen.py
yta_multimedia/alphascreen/consts.py
yta_multimedia/alphascreen/image_alphascreen.py
yta_multimedia/alphascreen/masked_clip_creator.py
yta_multimedia/alphascreen/video_alphascreen.py
yta_multimedia/experimental/__init__.py
yta_multimedia/experimental/text/__init__.py
yta_multimedia/experimental/text/ai_prompt_handler.py
yta_multimedia/experimental/text/gemini_ai.py
yta_multimedia/experimental/video/__init__.py
yta_multimedia/experimental/video/projection_3d.py
yta_multimedia/greenscreen/__init__.py
yta_multimedia/greenscreen/classes/__init__.py
yta_multimedia/greenscreen/classes/greenscreen_area_details.py
yta_multimedia/greenscreen/classes/greenscreen_details.py
yta_multimedia/greenscreen/consts.py
yta_multimedia/greenscreen/custom/__init__.py
yta_multimedia/greenscreen/custom/greenscreen.py
yta_multimedia/greenscreen/custom/image_greenscreen.py
yta_multimedia/greenscreen/custom/threed_greenscreen.py
yta_multimedia/greenscreen/custom/utils.py
yta_multimedia/greenscreen/custom/video_greenscreen.py
yta_multimedia/greenscreen/enums.py
yta_multimedia/greenscreen/green_screen_image.py
yta_multimedia/greenscreen/titled_green_screen_image.py
yta_multimedia/greenscreen/utils.py
yta_multimedia/resources/__init__.py
yta_multimedia/resources/audio/__init__.py
yta_multimedia/resources/audio/drive_urls.py
yta_multimedia/resources/image/__init__.py
yta_multimedia/resources/image/background/__init__.py
yta_multimedia/resources/image/background/drive_urls.py
yta_multimedia/resources/image/drive_urls.py
yta_multimedia/resources/image/greenscreen/__init__.py
yta_multimedia/resources/video/__init__.py
yta_multimedia/resources/video/background/__init__.py
yta_multimedia/resources/video/background/drive_urls.py
yta_multimedia/resources/video/effect/__init__.py
yta_multimedia/resources/video/effect/sound/__init__.py
yta_multimedia/resources/video/effect/sound/drive_urls.py
yta_multimedia-0.2.1.dist-info/LICENSE
yta_multimedia-0.2.1.dist-info/METADATA
yta_multimedia-0.2.1.dist-info/WHEEL
yta_multimedia-0.2.1.dist-info/RECORD
