Metadata-Version: 2.3
Name: yta-multimedia
Version: 0.2.1
Summary: Youtube Autónomo Multimedia Module is here.
Author: danialcala94
Author-email: danielalcalavalera@gmail.com
Requires-Python: ==3.9
Classifier: Programming Language :: Python :: 3
Classifier: Programming Language :: Python :: 3.9
Requires-Dist: backgroundremover (>=0.2.6,<1.0.0)
Requires-Dist: imageio (>=2.33.0,<3.0.0)
Requires-Dist: matplotlib (>=3.8.4,<4.0.0)
Requires-Dist: moviepy (>=2.0.0,<3.0.0)
Requires-Dist: numba (>=0.60.0,<1.0.0)
Requires-Dist: opencv-python (>=4.11.0.86,<5.0.0.0)
Requires-Dist: pillow (>=9.5.0,<10.0.0)
Requires-Dist: pygame (>=2.5.2,<3.0.0)
Requires-Dist: scenedetect (>=0.6.5.1,<1.0.0.0)
Requires-Dist: scikit-image (>=0.22.0,<1.0.0)
Requires-Dist: scipy (>=1.13.1,<2.0.0)
Requires-Dist: yta_audio (>=0.0.29,<1.0.0)
Requires-Dist: yta_colors (>=0.0.1,<1.0.0)
Requires-Dist: yta_constants (>=0.0.1,<1.0.0)
Requires-Dist: yta_file_downloader (>=0.0.1,<1.0.0)
Requires-Dist: yta_general_utils (>=0.0.1,<1.0.0)
Requires-Dist: yta_image (>=0.0.10,<1.0.0)
Requires-Dist: yta_multimedia_ffmpeg_handler (>=0.0.1,<1.0.0)
Requires-Dist: yta_multimedia_utils (>=0.0.1,<1.0.0)
Requires-Dist: yta_programming (>=0.0.1,<1.0.0)
Requires-Dist: yta_temp (>=0.0.1,<1.0.0)
Requires-Dist: yta_validation (>=0.0.1,<1.0.0)
